{
  "secciones": {
    "asunto": "I. ASUNTO\nSe pronuncia la Sala respecto al recurso de apelación\ninterpuesto por el abogado defensor del acusado MARIO\nFERNANDO BENAVIDES JIMÉNEZ, exgobernador\nencargado del departamento de Nariño, contra la decisión\nproferida por la Sala Especial de Primera Instancia de la\nCorte Suprema de Justicia el 10 de junio de 2025, mediante\nla cual ordenó la realización virtual de la etapa probatoria del\njuicio oral.",
    "actuacion_procesal_relevante": "II. ACTUACIÓN PROCESAL RELEVANTE\n1. El 29 de noviembre de 2017, ante una Magistrada del\nTribunal Superior de Bogotá, la Fiscalía Delegada ante la\nCUI: 11001 60 00102 2016 00502 04\nNÚMERO INTERNO 69531\nSEGUNDA INSTANCIA\nCAMILO ROMERO GALEANO Y OTRO\nCorte Suprema de Justicia, previa descripción de los hechos\njurídicamente relevantes, formuló imputación en contra de\nCAMILO ERNESTO ROMERO GALEANO y MARIO\nFERNANDO BENAVIDES JIMÉNEZ como autores de los\ndelitos de (i.) falsedad ideológica de documento público, (ii.)\ninterés indebido en la celebración de contratos, (iii.) contrato\nsin cumplimiento de los requisitos legales y (iv.) asociación\npara la comisión de un delito contra la administración\npública; así como también, como determinadores del punible\nde (v.) falsedad material de documento público, conductas\npunibles descritas en los artículos 286, 287 inciso 2, 409,\n410, 434 del Código Penal. Adicionalmente atribuyó a los\nimplicados las circunstancias de mayor punibilidad\nestablecidas en el artículo 58 numerales 1 y 10 del Código\nPenal (en virtud de la posición distinguida en la sociedad de\nlos actores y por haber actuado en coparticipación criminal),\núltima que exceptuó para el ilícito de asociación.\nSeguidamente y previa advertencia de los derechos que les\nasistían, ambos procesados manifestaron no aceptar los\ncargos.1\n2. Continuando con el trámite procesal ordinario, el 23\nde marzo de 2018, la Fiscalía General de la Nación presentó\nescrito de acusación, el cual verbalizó en audiencia\nestablecida para tal fin, adelantada el 18 de septiembre de\n1 Cfr. registro de audiencia de imputación celebrada el 29 de noviembre de 2017,\nobrante en CD que reposa a folio 1077 del Cuaderno Original Sala de Primera\nInstancia No. 6.\n2\nCUI: 11001 60 00102 2016 00502 04\nNÚMERO INTERNO 69531\nSEGUNDA INSTANCIA\nCAMILO ROMERO GALEANO Y OTRO\n2019, siendo reiterados los cargos imputados fáctica y\njurídicamente en audiencia preliminar.\n3. El 22 de enero de 2020 se instaló la audiencia\npreparatoria, en desarrollo de la cual a través de decisión de\n1º de junio de 2021 se resolvieron las solicitudes probatorias;\nprovidencia que esta Sala de Casación Penal, al desatar el\nrecurso de apelación interpuesto por la defensa técnica de\nambos procesados, la revocó parcialmente y confirmó en\nalgunos apartes mediante AP5342 de 10 de noviembre de\n2021.\n4. Instalado el juicio oral, en sesión de 22 de marzo de\n2022, el apoderado de ROMERO GALEANO elevó petición de\nnulidad de lo actuado a partir de las sustentaciones de los\nrecursos de reposición y apelación interpuestos por su\nprohijado y el entonces apoderado de éste en contra del auto\nque resolvió las solicitudes probatorias.\nDespachada desfavorablemente la pretensión\nanulatoria por los jueces de primera instancia e interpuesto\nel recurso vertical, esta Sala la confirmó mediante\nprovidencia AP1663 de 27 de abril de 2022.\n5. En sesión de audiencia de 06 de diciembre de 2022,\nel representante legal del mismo acusado elevó nueva\npetición de nulidad, la cual, el 07 de febrero de 2023 fue\nrechazada de plano por el a-quo, suerte idéntica que tuvo el\nrecurso de queja interpuesto por la misma parte.\n3\nCUI: 11001 60 00102 2016 00502 04\nNÚMERO INTERNO 69531\nSEGUNDA INSTANCIA\nCAMILO ROMERO GALEANO Y OTRO\n6. El 01 de marzo de 2023 el procesado CAMILO\nERNESTO ROMERO GALEANO sustentó recusación en\ncontra del magistrado ponente de primera instancia, la cual\nfue resuelta mediante auto de 26 de julio siguiente, leída en\naudiencia de 01 de agosto de 2023.\n7. Convocadas las partes para iniciar la práctica\nprobatoria, en sesión de audiencia adelantada el 16 de junio\ndel año en curso, el magistrado ponente dio lectura al auto\nque hoy constituye objeto del recurso de apelación\ninterpuesto por la defensa del acusado MARIO FERNANDO\nBENAVIDES JIMÉNEZ, a través del cual dispuso el\nadelantamiento del juicio oral de manera virtual.",
    "decision_impugnada": "III. DECISIÓN IMPUGNADA\nImpulsó el auto impugnado el oficio presentado ante la\nSala Especial de la Corte por parte de la Fiscal Primera\nDelegada ante esta Corporación, a través del cual remitía el\nlistado de testigos a intervenir en las fechas programadas\npara el juicio oral, advirtiendo que aquellos se presentarían\n«personalmente en la sala de audiencias».\nFrente a éste, afirmó el a-quo encontrarse ante una\nsucesión de normas de carácter instrumental o ritual\nrespecto a:\n4\nCUI: 11001 60 00102 2016 00502 04\nNÚMERO INTERNO 69531\nSEGUNDA INSTANCIA\nCAMILO ROMERO GALEANO Y OTRO\n- Por una parte, lo reglado por los artículos 1 (parágrafo\n4) y 7 (incisos 4 y 5) de la Ley 2213 de 2022 que, en últimas,\naunque mantiene el principio de presencialidad como regla\nen la especialidad penal de la jurisdicción ordinaria, permite\nla virtualidad a través del uso de tecnologías de la\ninformación.\n- Y por otra, los cánones 122 y 123 de la Ley\nEstatutaria de la Administración de Justicia, modificados\nrespectivamente por los artículos 62 y 63 de la Ley 2430 de\n2024, vigentes a partir del 09 de octubre del mismo año, de\nacuerdo con los cuales y siguiendo la interpretación de la\nCorte Constitucional, «a partir de la vigencia de la\nmodificación de dichas normas, las audiencias y diligencias\nque tienen como propósito la práctica de pruebas, por regla\ngeneral deben celebrarse presencialmente, salvo los casos\nexcepcionalmente permitidos y aquello en que, por razones de\nfuerza mayor debidamente justificadas así lo impongan».\nPor tal razón, con el fin de evitar «inconvenientes que\npudieran eventualmente sobrevenir con la aplicación de la\nnueva ley – que para el caso impone el cambio de modalidad\nde virtual a presencial – con todo lo que ello implica desde los\nprincipios de celeridad y eficacia de la función de administrar\njusticia, la concurrencia de testigos que se ubican en otro\ndepartamento, las demoras en su comparecencia […]», dispuso\nla Sala Especial dar aplicación a lo reglado por el artículo 40\nde la Ley 153 de 1883, modificado por el artículo 624 del\nCódigo General del Proceso, el cual reza:\n5\nCUI: 11001 60 00102 2016 00502 04\nNÚMERO INTERNO 69531\nSEGUNDA INSTANCIA\nCAMILO ROMERO GALEANO Y OTRO\n«Las leyes concernientes a la sustanciación y\nritualidad de los juicios prevalecen sobre las anteriores\ndesde el momento en que deben empezar a regir.\nSin embargo, los recursos interpuestos, la práctica de\npruebas decretadas, las audiencias convocadas, las diligencias\niniciadas, los términos que hubieren comenzado a correr, los\nincidentes en curso y las notificaciones que se estén surtiendo, se\nregirán por las leyes vigentes cuando se interpusieron los\nrecursos, se decretaron las pruebas, se iniciaron las audiencias\no diligencias, empezaron a correr los términos, se promovieron los\nincidentes o comenzaron a surtirse las notificaciones. […]».\n(resaltado de la Corte).\nAsí, «atendiendo a que las pruebas fueron decretadas y\nse vienen llevando a cabo de conformidad con la normativa\nque permitía adelantar el juicio oral virtualmente, se debe\ncontinuar su práctica hasta culminarla, de acuerdo con las\nreglas anteriores». Dispuso entonces adelantar el trámite del\njuicio oral de manera virtual, bajo la vigencia de lo que\ndenominó la «ley anterior».\nFinalmente, por considerar que se trata de un auto que\nresuelve aspectos sustanciales, la Sala de Primera Instancia\nhabilitó la interposición de los recursos ordinarios en contra\nde su decisión, frente a la cual, el apoderado de MARIO\nFERNANDO BENAVIDES JIMÉNEZ interpuso el recurso de\napelación.",
    "sustentacion_recurso": "IV. SUSTENTACIÓN DEL RECURSO\nSostiene el censor que la reforma a la Ley Estatutaria\nde Administración de Justicia, así como su revisión a través\nde la sentencia C-134-2023 dejó clara la constitucionalidad\n6\nCUI: 11001 60 00102 2016 00502 04\nNÚMERO INTERNO 69531\nSEGUNDA INSTANCIA\nCAMILO ROMERO GALEANO Y OTRO\ncondicionada de las normas incorporadas a través de los\nartículos 62 y 63 de Ley 2430 de 2024 «en el sentido de que\nla práctica probatoria en materia penal debe ser presencial por\naquello de garantizar de alguna manera la contradicción y la\ninmediación en plenitud».\nManifiesta no compartir la aplicación del artículo 40 de\nla Ley 153 de 1887, cuando la regla general en materia penal\nsiempre ha sido la práctica presencial de la prueba.\nAdicionalmente, estima que el criterio de la Sala\nEspecial de Primera instancia termina privilegiando la\nceleridad y eficacia, sobre las garantías fundamentales de\ncontradicción e inmediación, principios mucho más ligados\nal debido proceso.\nAdicionalmente, no comprende cómo el planteamiento\nde la Fiscalía, que manifestó que los testigos se presentarían\nante la Corte de forma presencial, fue el que motivó el\npronunciamiento del a-quo, que sin elementos de juicio\nplanteó «dificultades en la concurrencia de testigos» y\n«eventual demora en la comparecencia».\nEstima que lo que corresponde es dar aplicación a la\nsentencia de la Corte Constitucional, la cual dejó en claro la\nnecesidad de privilegiar las garantías a la defensa e\ninmediación entre otros, frente a la celeridad y eficacia que\npodría representar la virtualidad.\n7\nCUI: 11001 60 00102 2016 00502 04\nNÚMERO INTERNO 69531\nSEGUNDA INSTANCIA\nCAMILO ROMERO GALEANO Y OTRO\nEn estos términos, solicitó a la Sala de Casación Penal\nde la Corte, la revocatoria de la decisión impugnada y en su\nlugar, «permitir la presencialidad en la continuación de este\njuicio».",
    "pronunciamiento_no_recurrentes": "V. PRONUNCIAMIENTO DE NO RECURRENTES\n1. El delegado de la Fiscalía encuentra «razonable y\nplausible» la interpretación llevada a cabo por la primera\ninstancia, al acudir en pro de los principios de eficacia y\nceleridad a lo reglado por el artículo 40 de la Ley 153 de 1887,\nmodificado por el artículo 624 del Código General del\nProceso.\nReconoce que en efecto, la práctica presencial de la\nprueba, podría generar graves traumatismos dentro de la\nactuación procesal, «sobre todo en cuanto a la comparecencia\nde los testigos», pudiéndose surtir «sin afectación a los\nderecho de defensa ni al principio de inmediación y mucho\nmenos a la confrontación probatoria a través de los\nmecanismos virtuales».\nDe tal forma, solicita confirmar la decisión impugnada.\n2. La apoderada de la Gobernación de Nariño no\nadvierte que la decisión objeto de recurso «cause agravio,\nperjuicio o indefensión a nuestra parte o que vulnere derecho\nalguno de los intervinientes», contribuyendo, por el contrario,\n«al desarrollo ordenado y eficiente del proceso en concordancia\n8\nCUI: 11001 60 00102 2016 00502 04\nNÚMERO INTERNO 69531\nSEGUNDA INSTANCIA\nCAMILO ROMERO GALEANO Y OTRO\ncon los lineamientos jurisprudenciales de la Corte Suprema de\nJusticia en la importancia de la celeridad y la transparencia\nen la Administración de Justicia».\n3. La representante del Ministerio Público manifestó\ncompartir el criterio expuesto por la Fiscalía, resaltando que\n«la virtualidad permite la utilización de los principios de\nceleridad y concentración que a su vez garantiza un juicio\npúblico en un plazo razonable y esto es importante también\npara los derechos de las víctimas, además es sabido por todos\nque la virtualidad permite una conexión y la concurrencia real\nde todos los intervinientes sin las complicaciones propias del\ntransporte, es lo que dice la sentencia C-134 de 2023 donde\nque concluye que esta decisión es potestativa del juez».\n4. El apoderado del acusado CAMILO ERNESTO\nROMERO GALEANO manifestó la validez de los argumentos\npresentados por el recurrente, dejando en claro que su\npostura siempre ha sido la de defender la virtualidad, por lo\nmenos en su caso, por razones particulares de seguridad.\n5. El apoderado de la Contraloría manifestó su\npreferencia a guardar silencio en el debate presentado.",
    "consideraciones": "VI. CONSIDERACIONES DE LA CORTE\n1. Correspondería a la Sala resolver el recurso de\napelación interpuesto, de no ser porque se advierte, que\n9\nCUI: 11001 60 00102 2016 00502 04\nNÚMERO INTERNO 69531\nSEGUNDA INSTANCIA\nCAMILO ROMERO GALEANO Y OTRO\nconforme a la ley vigente, contra la determinación acerca de\nla modalidad a adelantar el juicio oral, en virtud de la\nnaturaleza de tal resolución, no proceden los recursos, como\nse pasa a exponer:\nEn efecto, conforme al artículo 1, parágrafo 4 de la\nLey 2213 de 2022, la decisión a través de la cual el juez\ndetermina el uso de las tecnologías de la información y las\ncomunicaciones en la especialidad penal, constituye una\n«orden», razón por la cual, expresamente lo señala la norma,\n«no caben recursos» en contra de ésta.\nNormativa que mantiene validez en el ordenamiento\nnacional, al no haber sido derogada por disposición posterior\nque disponga lo contrario y por constituir, en palabras de la\nCorte Constitucional en sentencia C-134 de 2023, ‘norma\nprocesal vigente’ y ‘referente normativo útil’.2\nAhora, si bien la sentencia aludida, indicó que, «frente a\nla decisión que adopte el juez en materia de presencialidad o\nvirtualidad los sujetos procesales tendrán los recursos que\ncontemple la ley procesal respectiva»,3 la Ley 2213 de\n2022, norma procesal vigente y «referente normativo útil»,\ncomo se indicó, dispone la improcedencia de cualquier\nrecurso en contra de la orden mediante la cual se decide\nsobre el uso de las tecnologías de la información en el proceso\n2 Cfr. Corte Constitucional, Sentencia C-134-2023, Nos. 1669 y 1682.\n3 Corte Constitucional, Sentencia C-134-2023, No. 1682.\n10\nCUI: 11001 60 00102 2016 00502 04\nNÚMERO INTERNO 69531\nSEGUNDA INSTANCIA\nCAMILO ROMERO GALEANO Y OTRO\npenal, como lo es, la disposición de realizar de manera virtual\no presencial la audiencia del juicio oral.\nEn tal virtud, la Sala se abstendrá de resolver la\nimpugnación propuesta.\n2. Sin embargo, ante la importancia del tema y la\ndiversidad de criterios que la actual práctica judicial aplica –\ncomo el aquí expuesto por la Sala Especial de Primera\nInstancia de esta Corporación— resulta necesario que la Sala\nde Casación Penal de la Corte, como máximo órgano de la\njurisdicción ordinaria en materia penal, aclare las reglas a\nseguir, observando en todo caso, la interpretación conforme\na la Constitución, desarrollada por la Corte Constitucional\nen el ya mencionado fallo.\nEn este punto, se encontraron dos incorrecciones\nfundamentales en la argumentación de la Sala Especial en\nsus argumentos, así:\n2.1. El a-quo erradamente entendió como\ncontrapuestos el contenido de: un lado, los\nartículos 1 (parágrafo 4) y 7 (incisos 3 y 4) de la Ley 2213 de\n2022; y de otro lado, de los reformados artículos 122 y 123 de\nla Ley Estatutaria de la Administración de Justicia. Veamos:\nLa Ley 2213 de 2022, en su artículo 1, parágrafo 4º\nestablece:\n11\nCUI: 11001 60 00102 2016 00502 04\nNÚMERO INTERNO 69531\nSEGUNDA INSTANCIA\nCAMILO ROMERO GALEANO Y OTRO\n«El uso de las tecnologías de la información y las comunicaciones\nen la especialidad penal de la jurisdicción ordinaria y penal\nmilitar, será evaluada y decidida autónomamente, mediante\norden, contra la que no caben recursos, conforme a la Ley\nEstatutaria de Administración de Justicia, por el Juez o\nMagistrado a cargo del respectivo proceso o actuación procesal».\nY postula en su artículo 7, incisos 3º y 4º:\n«Para el caso de la jurisdicción penal, de manera oficiosa el\njuez de conocimiento podrá disponer la práctica presencial de la\nprueba cuando lo considere necesario, y deberá disponerlo así\ncuando alguna de las partes se lo solicite, sin que las mismas\ndeban motivar tal petición. Excepcionalmente la prueba podrá\npracticarse en forma virtual ante la imposibilidad comprobada\npara garantizar la comparecencia presencial de un testigo, experto\no perito al despacho judicial.\nLa presencia física en la sede del juzgado de conocimiento\nsolo será exigible al sujeto de prueba, a quien requirió la práctica\npresencial y al juez de conocimiento, sin perjuicio de que puedan\nasistir de manera presencial los abogados reconocidos, las partes\nque no deban declarar, los terceros e intervinientes especiales y\ndemás sujetos del proceso, quienes además podrán concurrir de\nmanera virtual».\nQuiere decir lo anterior que de acuerdo con la Ley 2213\nde 2022, tratándose de la especialidad penal y en concreto\nen lo que respecta a la práctica probatoria, la regla es:\nEs potestativo del juez penal determinar la\nforma – virtual o presencial – de la práctica probatoria.\nPodrá (facultativo) acudir a la modalidad presencial,\ncuando:\n1. Lo considere necesario\nY deberá (mandato) disponer la presencialidad cuando:\n2. Alguna de las partes se lo solicite\n12\nCUI: 11001 60 00102 2016 00502 04\nNÚMERO INTERNO 69531\nSEGUNDA INSTANCIA\nCAMILO ROMERO GALEANO Y OTRO\nConstituyendo excepción a la regla:\n3. La imposibilidad comprobada para garantizar la\ncomparecencia presencial del testigo, experto o perito,\ncaso en el cual, podrá practicar la prueba de manera\nvirtual.\nAhora, la Ley Estatutaria de la Administración de\nJusticia, modificada por la Ley 2430 de 2024, en lo que fue\nasunto de debate establece:\n«Artículo 122. USO DE LAS TECNOLOGÍAS DE LA\nINFORMACIÓN Y LAS COMUNICACIONES.\n[…]\nSe utilizarán los medios tecnológicos para todas las\nactuaciones judiciales, sin perjuicio de la necesaria presencia\nen las audiencias y diligencias destinadas a la práctica de\npruebas, y se permitirá a los sujetos procesales actuar en los\nprocesos o trámites a través de los medios digitales disponibles,\nevitando exigir formalidades presenciales o similares, que no sean\nestrictamente necesarias.\n[…]\nPARÁGRAFO 2. […] serán presenciales las audiencias y\ndiligencias destinadas a la práctica de pruebas, con excepción de\nlos casos expresa y excepcionalmente permitidos en la ley procesal\nrespectiva, cuando las circunstancias así lo imponga.\nIgualmente, por razones de imparcialidad, necesidad o\ninmediación la autoridad judicial podrá tramitar presencialmente\nalguna o toda la actuación judicial. […]»\nArtículo 123: DEBERES DE LOS SUJETOS PROCESALES EN\nRELACIÓN CON LAS TECNOLOGÍAS DE LA INFORMACIÓN Y LAS\nCOMUNICACIONES.\nEn todos los procesos judiciales, adelantados por los\ndespachos judiciales y por otras autoridades con funciones\njurisdiccionales, en los cuales se haya adoptado el uso de\ntecnologías de información y las comunicaciones, el operador\njurídico podrá disponer que el proceso judicial se adelantará a\ntravés de ellas, en cuyo caso será deber de los sujetos procesales\n13\nCUI: 11001 60 00102 2016 00502 04\nNÚMERO INTERNO 69531\nSEGUNDA INSTANCIA\nCAMILO ROMERO GALEANO Y OTRO\nrealizar sus actuaciones y asistir a las audiencias y diligencias a\ntravés de medios tecnológicos, [salvo el caso de las destinadas a\nla práctica de pruebas que serán siempre presenciales, a menos\nque la norma procesal expresa y excepcionalmente permita la\naudiencia probatoria virtual]. (Aparte entre corchetes declarado\ninconstitucional, Sentencia C134-2023).\nLuego entonces de acuerdo con la normativa de 2024:\nUNO: Según el inciso 4º del artículo 122, la regla es la\nutilización de los medios tecnológicos en todas las\nactuaciones judiciales. La excepción: Opera la\npresencialidad, cuando ello es necesario para la práctica de\npruebas.\nDOS: Según el Parágrafo 2 del artículo 122, la regla es\nque las audiencias destinadas a la práctica de pruebas serán\npresenciales. La excepción: los casos expresa y\nexcepcionalmente permitidos en la ley procesal respectiva.\nY en este aspecto, vale la pena recordar, que la Ley 2213\nde 2022, constituye ‘norma procesal vigente’ e incluso\n‘referente normativo útil’. Por lo tanto los criterios de la ley de\n2022 se encuentran amparados por la ley de rango superior\nde 2024.\nY TRES: Según el inciso 2º del Parágrafo 2 citado y el\nartículo 123 de la misma Ley Estatutaria, es potestativo del\njuez tramitar presencialmente la actuación judicial, por\nrazones de necesidad o inmediación.\n14\nCUI: 11001 60 00102 2016 00502 04\nNÚMERO INTERNO 69531\nSEGUNDA INSTANCIA\nCAMILO ROMERO GALEANO Y OTRO\nSe concluye, entonces, comparadas las normas de 2022\ny 2024, que aquellas contienen significado similar en lo\nfundamental: ambas coinciden en la facultad del juez para\nseleccionar la modalidad de la audiencia destinada a la\npráctica probatoria, teniendo en cuenta, para ambos casos\nnormativos, el criterio de necesidad, entre otros, al\nmomento de decantarse por aquella de carácter presencial.\nDe acuerdo con lo hasta aquí analizado, entonces, no\nresulta acertado acudir a las «REGLAS GENERALES SOBRE\nVALIDEZ Y APLICACIÓN DE NORMAS» establecidas por la Ley 153\nde 1887, en concreto al artículo 40 invocado por la\nCorporación de primera instancia, en tanto su aplicación, de\nacuerdo con el artículo 1 ibídem ocurre cuando se presenta:\n- Incongruencia entre dos leyes\n- Oposición entre la ley anterior y la ley posterior; o\n- Trate de establecerse el tránsito legal de derecho\nantiguo a derecho nuevo.\nEventualidades que como quedó visto, no tienen lugar\npara el caso de las Leyes 2213 de 2022 y Ley 2430 de 2024.\n2.2. De otra parte, omitió la Sala Especial de Primera\nInstancia, tanto la interpretación realizada por la Corte\nConstitucional en ejercicio de su facultad de control previo\nsobre la leyes estatutarias, a los artículos 62 y 63 de la\nLey 2430 de 2022, como el consecuentemente deber de dar\naplicación de aquella a partir del momento de entrada en\n15\nCUI: 11001 60 00102 2016 00502 04\nNÚMERO INTERNO 69531\nSEGUNDA INSTANCIA\nCAMILO ROMERO GALEANO Y OTRO\nvigencia de la reforma a la Ley Estatutaria (09 de octubre de\n2024) y la extensión de tal interpretación, por identidad de\nmateria, a la normativa correspondiente de la Ley 2213 de\n2022, en todo caso, esta última, de menor jerarquía que\naquella con carácter de “estatutaria”.\nEn efecto, la Corte Constitucional, frente a la\nindeterminación normativa provocada por el texto de los\nartículos 63 y 64 del Proyecto de Reforma de la Ley\nEstatutaria de la Administración de Justicia (PLRLEAJ), en\ntanto «no es claro si con ellas se establece una obligación de\npresencialidad absoluta en la práctica de pruebas o si solo es\nnecesaria en algunos supuestos», expuso los siguientes\nargumentos, relevantes para resolver el caso:\n«1676. Por ello, considera la Corte que frente a las diferentes\ninterpretaciones sobre la manera de practicar las pruebas que\nsurgen de los artículos 63 y 64, debe preferirse una interpretación\nflexible de estas dos normas, pero que no impongan una camisa\nde fuerza en un sentido u otro. En otras palabras, el estándar\nmínimo procesal debe ser la autonomía razonada del juez para\ndeterminar el mejor camino para el desarrollo del proceso de\nacuerdo con criterios de imparcialidad, necesidad o inmediación.\n1677. No obstante, frente a esta regla, la Corte considera,\ncomo única excepción, la audiencia de juicio oral contemplada en\nla especialidad penal de la jurisdicción ordinaria, que deberá ser\npresencial, a menos que por motivos de fuerza mayor,\ndebidamente acreditado ante el juez, se concluya que la persona -\nsea parte, interviniente o testigo- puede comparecer a la audiencia\nde manera virtual sin que esto afecte el adecuado desarrollo del\njuicio oral, lo cual deberá ser valorado por el juez de conocimiento.\nA título meramente ilustrativo, esta situación podría presentarse\nante una condición grave de salud que le impida a la persona\ndesplazarse de su lugar de residencia; cuando haya serios\nmotivos de seguridad que aconsejen evitar su desplazamiento; por\nla declaratoria de un estado de emergencia sanitaria en que se\ndisponga como medida la celebración virtual de todas las\nactuaciones procesales; por la existencia de regulaciones\n16\nCUI: 11001 60 00102 2016 00502 04\nNÚMERO INTERNO 69531\nSEGUNDA INSTANCIA\nCAMILO ROMERO GALEANO Y OTRO\nespeciales que exijan la adopción de medidas para no exponer a\nla víctima frente al presunto agresor, o por compromisos\ninternacionales del Estado colombiano en virtud de tratados de\ncooperación judicial que privilegien la realización de audiencias\nvirtuales como instrumento para materializar la asistencia entre\nEstados, entre otras múltiples y muy diversas circunstancias\nexcepcionales que puedan presentarse y que el juez deberá valorar\nen su momento.\n1678. La decisión de la Corte de preservar la presencialidad\npara la audiencia del juicio oral en materia penal se adopta como\nuna medida encaminada a proteger las garantías básicas de la\nintegridad, legalidad, derecho de defensa e inmediación en la\nvaloración de las pruebas y el debate probatorio, que se\nencuentran estrechamente ligadas con la construcción de la\nverdad. Por otra parte, la Corte resalta que el proceso penal tiene\nuna particularidad que no existe en otro tipo de actuaciones\njudiciales, ya que la libertad personal de quien está siendo\nprocesado puede resultar comprometida con la declaratoria de\nresponsabilidad y la imposición de una pena de prisión, la sanción\nmás grave que prevé el ordenamiento jurídico. Sumado a ello, y no\nmenos importante, está el interés de la sociedad en general, y de\nlas víctimas en particular, en que se esclarezcan y sancionen los\nhechos que afectan más gravemente a las personas.».4\nEn síntesis, luego de resaltar los riesgos que apareja la\ncelebración virtual de la práctica probatoria para la correcta\nconstrucción de la verdad para el ejercicio de las\nmanifestaciones básicas del derecho de defensa, la Corte\nConstitucional estableció:\nUNO. Como regla general, tratándose de práctica de\npruebas –en todas las especialidades— una interpretación\nflexible de los artículos 63 y 64 PLEAJ, traducida en la\nautonomía razonada del juez para determinar la mejor\nopción (virtual o presencial) para el desarrollo del proceso, de\n4 Corte Constitucional, C-134 de 2023. Disponible en el link\nhttps://www.corteconstitucional.gov.co/relatoria/2023/c-134-23.htm.\n17\nCUI: 11001 60 00102 2016 00502 04\nNÚMERO INTERNO 69531\nSEGUNDA INSTANCIA\nCAMILO ROMERO GALEANO Y OTRO\nacuerdo con criterios de imparcialidad, necesidad o\ninmediación.\nDOS. La audiencia de juicio oral contemplada en la\nespecialidad penal, deberá ser presencial (regla general).\nY TRES: La excepción a la obligatoriedad de la\npresencialidad en la práctica de pruebas en el juicio oral\nen materia penal. se construye en casos de ‘fuerza mayor\ndebidamente acreditada ante el juez’, que permita concluir\nque la persona (parte, interviniente o testigo) puede\ncomparecer a la audiencia de manera virtual sin afectar el\nadecuado desarrollo del juicio.\nLuego entonces, es bajo tales criterios de interpretación\nconforme a la Constitución, que es deber de los jueces aplicar\nel contenido de tanto de los artículos 1 (parágrafo 4) y 7 (incisos\n3 y 4) de la Ley 2213 de 2022, como de los reformados\ncánones 122 y 123 de la Ley Estatutaria de la Administración\nde Justicia, a partir de la entrada en vigencia de esta última\nnormativa, esto es, del 09 de octubre de 2024.\nQuiere entonces dejar en claro la Sala de Casación\nPenal, que tratándose de esta especialidad, la audiencia de\npráctica probatoria del juicio oral, debe ser presencial.\nEsto, en aras de garantizar principios fundamentales\ndel proceso penal, enfocados a la construcción de una verdad\nprocesal lo más cercana posible a realidad material de lo\n18\nCUI: 11001 60 00102 2016 00502 04\nNÚMERO INTERNO 69531\nSEGUNDA INSTANCIA\nCAMILO ROMERO GALEANO Y OTRO\nacontecido, de tal forma que sea posible preservar tanto los\nderechos de las víctimas, como los derechos del procesado,\nlo que a su vez se traduce en el aseguramiento de los\nderechos a la defensa y a la obtención de justicia por parte\nde quienes resultaron afectados con el delito. Recuérdese\nadicionalmente, como lo resaltó la Corte Constitucional, que\nes el derecho penal el área del ordenamiento jurídico que más\ngraves consecuencias trae para la persona, traducidas en la\nimposición de penas privativas de la libertad.\nEs por ello que con el fin de evitar los riesgos que una\npráctica probatoria ‘virtual’ puede traer consigo, como\nresultan ser: el incumplimiento al interrogatorio por\nseparado de testigos, la consulta de documentos sin\nautorización del juez, la posible sugestión al testigo por un\ntercero cuya presencia no percibe el juez, la insuficiencia de\nelementos para una correcta apreciación del testimonio, la\nocurrencia de problemas de conexión que impidan el\ncontrainterrogatorio del testigo por la contraparte y la\nimposibilidad de que el acusado tenga una comunicación\nlibre y fluida con su defensor en el desarrollo de la práctica\nprobatoria, entre muchos otros, y por estar correlacionada\nlas resultas del proceso con la garantía fundamental a la\nlibertad, es por lo que debe primar la práctica de pruebas de\nmanera presencial.5\n5 En este sentido también, Corte Constitucional, Sentencia C-134-2023, No. 1678-\n1681.\n19\nCUI: 11001 60 00102 2016 00502 04\nNÚMERO INTERNO 69531\nSEGUNDA INSTANCIA\nCAMILO ROMERO GALEANO Y OTRO\nRegla que en todo caso, en interpretación ‘conforme a la\nConstitución’ de la normativa, tiene como excepción, el\nsurgimiento de motivos de fuerza mayor acreditados ante el\njuez, como lo pueden ser la imposibilidad de desplazamiento\ndel testigo por razones ajenas a su voluntad (salud,\nseguridad, declaratoria de estados de emergencia, falta de\nrecursos y similares) e incluso, la imperiosa necesidad de\nagilizar el trámite procesal ante la inminente prescripción de\nla acción penal, cuando se observe que la dificultad de la\nrealización presencial de la práctica probatoria pueda\ntornarse en factor dilatorio, entre otras posibles categorías de\nanáloga comparación.\nEn todo caso, la virtualidad excepcional que es posible\nde ser decretada por el Juez o Magistrado, conforme a las\nreglas atrás descritas, no es, de ninguna manera, una\nfacultad para eximir el deber Estatutario y la obligación legal\ny constitucional que tienen los Funcionarios Judiciales de\nestar presencialmente en sus Despachos Judiciales como\ndirectores del Servicio Público de Administración de Justicia\ncon el que simbólica y realmente representan al Estado\nColombiano, como quiera que su función pública se ejerce en\nnombre de la República y por Autoridad de la Ley.\nEn mérito de lo expuesto, la Corte Suprema de Justicia,\nSala de Casación Penal,\nRESUELVE:\n20\nCUI: 11001 60 00102 2016 00502 04\nNÚMERO INTERNO 69531\nSEGUNDA INSTANCIA\nCAMILO ROMERO GALEANO Y OTRO\nAbstenerse de resolver el recurso de apelación\ninterpuesto contra la decisión de 10 de junio de 2025\nproferida por la Sala Especial de Primera Instancia de esta\nCorporación.\nContra esta decisión no procede recurso alguno.\nCOMUNÍQUESE Y CÚMPLASE\nMYRIAM ÁVILA ROLDÁN\nPresidenta de la Sala\nNo firma impedimento\nGERARDO BARBOSA CASTILLO\nNo firma impedimento\n21\nCUI: 11001 60 00102 2016 00502 04\nNÚMERO INTERNO 69531\nSEGUNDA INSTANCIA\nCAMILO ROMERO GALEANO Y OTRO\nJORGE HERNÁN DÍAZ SOTO\nNo firma impedimento\nEste documento fue generado con firma electrónica y cuenta con plena validez jurídica, conforme a lo dispuesto\nen artículo 103 del Código General del Proceso y el artículo 7 de la ley 527 de 1999\nCódigo de verificación: F69D8C475A5C8C0CAE5CF878D5CC13EFE2F96DC8098B23197BFA77DD7755B724\nDocumento generado en 2025-07-16\n22",
    "fallo": ""
  },
  "analisis": {
    "asunto": {
      "entidades": {
        "PERSONAS": [],
        "ORGANIZACIONES": [
          "Sala Especial de Primera Instancia",
          "Corte Suprema de Justicia"
        ],
        "FECHAS": [],
        "LUGARES": [
          "MARIO FERNANDO BENAVIDES JIMÉNEZ",
          "Nariño",
          "departamento de"
        ]
      }
    },
    "actuacion_procesal_relevante": {
      "entidades": {
        "PERSONAS": [],
        "ORGANIZACIONES": [
          "ROMERO GALEANO",
          "OTRO Corte Suprema de Justicia",
          "Fiscalía General de la Nación"
        ],
        "FECHAS": [],
        "LUGARES": [
          "MARIO FERNANDO BENAVIDES JIMÉNEZ",
          "Fiscalía Delegada",
          "CAMILO ERNESTO ROMERO GALEANO",
          "Tribunal Superior de Bogotá"
        ]
      },
      "hechos_relevantes": [
        "El 29 de noviembre de 2017, ante una Magistrada del\nTribunal Superior de Bogotá, la Fiscalía Delegada ante la\nCUI: 11001 60 00102 2016 00502 04\nNÚMERO INTERNO 69531\nSEGUNDA INSTANCIA\nCAMILO ROMERO GALEANO Y OTRO\nCorte Suprema de Justicia, previa descripción de los hechos\njurídicamente relevantes, formuló imputación en contra de\nCAMILO ERNESTO ROMERO GALEANO y MARIO\nFERNANDO BENAVIDES JIMÉNEZ como autores de los\ndelitos de (i.) falsedad ideológica de documento público, (ii.",
        "Continuando con el trámite procesal ordinario, el 23\nde marzo de 2018, la Fiscalía General de la Nación presentó\nescrito de acusación, el cual verbalizó en audiencia\nestablecida para tal fin, adelantada el 18 de septiembre de\n1 Cfr.",
        "asociación\npara la comisión de un delito contra la administración\npública; así como también, como determinadores del punible\nde (v.) falsedad material de documento público, conductas\npunibles descritas en los artículos 286, 287 inciso 2, 409,\n410, 434 del Código Penal.",
        "El 01 de marzo de 2023 el procesado CAMILO\nERNESTO ROMERO GALEANO sustentó recusación en\ncontra del magistrado ponente de primera instancia, la cual\nfue resuelta mediante auto de 26 de julio siguiente, leída en\naudiencia de 01 de agosto de 2023.\n7.",
        "Seguidamente y previa advertencia de los derechos que les\nasistían, ambos procesados manifestaron no aceptar los\ncargos.1\n2.",
        "registro de audiencia de imputación celebrada el 29 de noviembre de 2017,\nobrante en CD que reposa a folio 1077 del Cuaderno Original Sala de Primera\nInstancia No.",
        "El 22 de enero de 2020 se instaló la audiencia\npreparatoria, en desarrollo de la cual a través de decisión de\n1º de junio de 2021 se resolvieron las solicitudes probatorias;\nprovidencia que esta Sala de Casación Penal, al desatar el\nrecurso de apelación interpuesto por la defensa técnica de\nambos procesados, la revocó parcialmente y confirmó en\nalgunos apartes mediante AP5342 de 10 de noviembre de\n2021.",
        "esta Sala la confirmó mediante\nprovidencia AP1663 de 27 de abril de 2022."
      ]
    },
    "decision_impugnada": {
      "entidades": {
        "PERSONAS": [],
        "ORGANIZACIONES": [
          "Fiscal Primera Delegada",
          "Corte Constitucional"
        ],
        "FECHAS": [],
        "LUGARES": [
          "MARIO FERNANDO BENAVIDES JIMÉNEZ",
          "Sala Especial",
          "la Ley"
        ]
      }
    },
    "sustentacion_recurso": {
      "entidades": {
        "PERSONAS": [],
        "ORGANIZACIONES": [
          "Corte Constitucional",
          "Sala Especial de Primera"
        ],
        "FECHAS": [],
        "LUGARES": [
          "la Ley"
        ]
      }
    },
    "pronunciamiento_no_recurrentes": {
      "entidades": {
        "PERSONAS": [],
        "ORGANIZACIONES": [
          "Administración de Justicia",
          "RECURRENTES",
          "Corte Suprema de Justicia"
        ],
        "FECHAS": [],
        "LUGARES": [
          "Ministerio Público",
          "la Ley"
        ]
      }
    },
    "consideraciones": {
      "entidades": {
        "PERSONAS": [
          "Sentencia C134-2023",
          "Recuérdese",
          "Eventualidades"
        ],
        "ORGANIZACIONES": [
          "OTRO Abstenerse",
          "Constitución",
          "USO",
          "Juez",
          "Sala Especial de Primera Instancia",
          "Servicio Público de Administración de Justicia",
          "Corte Constitucional",
          "Normativa",
          "Oposición",
          "Corte Suprema de Justicia",
          "PLRLEAJ",
          "CÚMPLASE",
          "Constitución’ de la normativa",
          "Sala Especial",
          "Autoridad de la Ley"
        ],
        "FECHAS": [],
        "LUGARES": [
          "Estados",
          "Estado colombiano",
          "OTRO JORGE HERNÁN DÍAZ SOTO No",
          "Estado Colombiano",
          "ÁVILA ROLDÁN Presidenta de la Sala No",
          "Sala de Casación Penal",
          "La Ley",
          "la Ley"
        ]
      },
      "normas_detectadas": [
        "ley 2213 de 2022",
        "ley 2430 de 2024",
        "ley 153 de 1887",
        "ley 2430 de 2022",
        "ley 527 de 1999",
        "artículo 1",
        "artículos 1",
        "artículos 122 y 123",
        "artículo 7",
        "artículo 122",
        "artículo 123",
        "artículo 40",
        "artículos 62 y 63",
        "artículos 63 y 64",
        "artículo 103",
        "código general del proceso",
        "sentencia c-134 de 2023",
        "sentencia c-134",
        "sentencia c134"
      ]
    },
    "fallo": {
      "entidades": {
        "PERSONAS": [],
        "ORGANIZACIONES": [],
        "FECHAS": [],
        "LUGARES": []
      },
      "resumen_fallo": {
        "fallo_resumido": [],
        "tipo_fallo": "DESCONOCIDO"
      }
    }
  },
  "metadatos": {
    "cui": "110016000102201600502",
    "numero_interno": "69531",
    "referencias": [
      "AP4465-2025",
      "AP5342",
      "AP1663"
    ],
    "fecha_sentencia": "10 de junio de 2025",
    "magistrado_ponente": null,
    "corporacion_sala": "Corte Suprema de Justicia"
  }
}